pysql_beam/__init__.py
pysql_beam/examples/__init__.py
pysql_beam/examples/cloud_sql_to_file.py
pysql_beam/sql_io/__init__.py
pysql_beam/sql_io/exceptions.py
pysql_beam/sql_io/sql.py
pysql_beam/sql_io/wrapper.py
pysql_beam-0.2.dist-info/LICENSE
pysql_beam-0.2.dist-info/METADATA
pysql_beam-0.2.dist-info/WHEEL
pysql_beam-0.2.dist-info/top_level.txt
pysql_beam-0.2.dist-info/RECORD
