Metadata-Version: 2.1
Name: pysql-beam
Version: 0.2
Summary: Apache beam mysql and postgres io connector in pure python
Home-page: https://bitbucket.org/dverma90/pysql-beam
Author: Deepak Verma
Author-email: yesdeepakverma@gmail.com
License: UNKNOWN
Keywords: apache-beam,mysql,postgres,python,io,source,sink,read,write,database
Platform: UNKNOWN
Classifier: Programming Language :: Python :: 3
Classifier: Programming Language :: Python :: 2.7
Classifier: Programming Language :: Python :: 3
Classifier: Programming Language :: Python :: 3
Classifier: Programming Language :: Python :: 3
Classifier: License :: OSI Approved :: MIT License
Classifier: Intended Audience :: Developers
Classifier: Operating System :: OS Independent
Requires-Dist: apache-beam (>=2.10<=2.12.0)
Requires-Dist: psycopg2-binary (==2.8.2)
Requires-Dist: pymysql[rsa] (==0.9.3)
Requires-Dist: requests (>=2.22.0)
